{"data":{"markdownRemark":{"html":"<p>If you are curious about some of the new features in CFMX8, Ian Smith <a href=\"http://www.downloadsquad.com/2007/04/24/9-ways-coldfusion-8-will-rule-web-development/\" target=\"_blank\" rel=\"nofollow noopener noreferrer\">posted</a> some of the new features that Ben Forta presented on last night in Seattle.</p>","frontmatter":{"title":"Ian Smith blogs about Ben Forta's presentation in Seattle","date":"17.01.2011","category":"Blog"},"timeToRead":1}},"pageContext":{"slug":"/ian-smith-blogs-about-ben-fortas-presentation-in-seattle","prev":{"fields":{"slug":"/j-query-empty-vs-blank-filters"},"frontmatter":{"title":"JQuery :empty vs :blank filters","category":"Blog"}},"next":{"fields":{"slug":"/j-query-1-4-presentation-slides-from-jax-code-camp-now-online"},"frontmatter":{"title":"JQuery 1.4 Presentation Slides from Jax Code Camp now Online","category":"Blog"}}}}