{"data":{"markdownRemark":{"html":"<p>John Lyons, a friend and co-worker of mine has figured out how to install CFMX 7 on the fedora core. He will be posting to this blog soon with instructions on how to configure CFMX and Apache 2.0.</p>\n<p>It is tricky, but you can get it to work by manually configuring the connector to Apache. Macromedia does support CFMX with Red Hat, but not the Fedora core. Fedora is meant to be more expiramental than the standard Red Hat distro.</p>","frontmatter":{"title":"Running CFMX 7 on the Fedora core","date":"17.01.2011","category":"Blog"},"timeToRead":1}},"pageContext":{"slug":"/running-cfmx-7-on-the-fedora-core","prev":{"fields":{"slug":"/interviewed-on-webdevdesign-podcast"},"frontmatter":{"title":"Interviewed on webdevdesign podcast","category":"Blog"}},"next":{"fields":{"slug":"/idea-integration-looking-for-sql-developers-with-ssis-experience"},"frontmatter":{"title":"Idea Integration looking for SQL developers with SSIS experience","category":"Blog"}}}}