{"data":{"markdownRemark":{"html":"<p>The next Jaxfusion user group meeting will be hosted by me and I will be covering XML features in ColdFusion, and features that have been added since 7. This presentation will also cover how to leverage Java to overcome the shortcomings of XML DOM. The meeting will be held at Vurv Technology in Jacksonville, FL on October third at 6:30 PM.</p>","frontmatter":{"title":"XML will be the topic at the next JaxFusion User Group meeting","date":"17.01.2011","category":"Blog"},"timeToRead":1}},"pageContext":{"slug":"/xml-will-be-the-topic-at-the-next-jax-fusion-user-group-meeting","prev":{"fields":{"slug":"/xml-search-comments-added-to-livedocs"},"frontmatter":{"title":"XMLSearch() comments added to Livedocs","category":"Blog"}},"next":{"fields":{"slug":"/xhtml-and-css-validation"},"frontmatter":{"title":"XHTML and CSS validation","category":"Blog"}}}}