{"data":{"markdownRemark":{"html":"<p>I am a board member of my local <a href=\"http://www.jaxrow.org\" target=\"_blank\" rel=\"nofollow noopener noreferrer\">rowing club</a> here in Jacksonville. When they found out I was a web developer, they asked me if I would work on their web site.</p>\n<p>Our hosting provider uses LAMP to host their web sites, so everything is Apache, PHP and MySQL. I have worked with MySQL and Apache before, but not so much with PHP. Since I know enough to be dangerous with PHP, I decided to try using one of the open source packages for blogging, so we could use blog software on the web site.</p>\n<p>I decided to use <a href=\"http://www.bblog.com/\" target=\"_blank\" rel=\"nofollow noopener noreferrer\">bBlog</a> for our blog. One of the things I noticed was how easy it was to install the different php projects that I came across. Most of these packages make it very easy to install on a LAMP site just using FTP and an HTML based wizard.</p>","frontmatter":{"title":"I am using php bloging software for jaxrow.org","date":"17.01.2011","category":"Blog"},"timeToRead":1}},"pageContext":{"slug":"/i-am-using-php-bloging-software-for-jaxrow-org","prev":{"fields":{"slug":"/xcode-4-preview-at-appleinsider-com"},"frontmatter":{"title":"Xcode 4 Preview at Appleinsider.com","category":"Blog"}},"next":{"fields":{"slug":"/xsd-validation-in-cfmx-6-1"},"frontmatter":{"title":"XSD validation in CFMX 6.1","category":"Blog"}}}}